playit/__init__.py
playit/cli.py
playit-0.2.dist-info/LICENSE.txt
playit-0.2.dist-info/METADATA
playit-0.2.dist-info/WHEEL
playit-0.2.dist-info/entry_points.txt
playit-0.2.dist-info/top_level.txt
playit-0.2.dist-info/RECORD
