Metadata-Version: 2.1
Name: playit
Version: 0.2
Summary: It play music on console in various mode.
Home-page: https://github.com/SaurabhGujjar/playit.git
Author: Saurabh Gujjar
Author-email: saurabhpanwar127@gmail.com
License: MIT
Download-URL: https://github.com/SaurabhGujjar/playit/archive/v_0.02.tar.gz
Keywords: music player,cli,command line interface
Platform: UNKNOWN
Classifier: Development Status :: 3 - Alpha
Classifier: Intended Audience :: Developers
Classifier: Topic :: Software Development :: Build Tools
Classifier: License :: OSI Approved :: MIT License
Classifier: Programming Language :: Python :: 3
Classifier: Programming Language :: Python :: 3.8
Classifier: Programming Language :: Python :: 3.6
Classifier: Programming Language :: Python :: 3.7
Requires-Dist: Click
Requires-Dist: pyfiglet
Requires-Dist: pygame
Requires-Dist: mutagen
Requires-Dist: tqdm
Requires-Dist: times
